djutils_rest/__init__.py
djutils_rest/requirements.txt
djutils_rest/api/__init__.py
djutils_rest/api/decorator.py
djutils_rest/api/default.py
djutils_rest/api/response.py
djutils_rest-0.1.0.dev0.dist-info/LICENSE
djutils_rest-0.1.0.dev0.dist-info/METADATA
djutils_rest-0.1.0.dev0.dist-info/WHEEL
djutils_rest-0.1.0.dev0.dist-info/top_level.txt
djutils_rest-0.1.0.dev0.dist-info/RECORD
