Metadata-Version: 2.1
Name: djutils-rest
Version: 0.1.0.dev0
Summary: Django Project Utilities - Rest API
Author-email: ruriazz <azizruri.s@gmail.com>
Project-URL: Homepage, https://github.com/ruriazz/djutils-rest
Project-URL: Bug Tracker, https://github.com/ruriazz/djutils-rest/issues
Keywords: djutils_rest
Classifier: Operating System :: OS Independent
Classifier: Programming Language :: Python
Classifier: Programming Language :: Python :: 3.11
Requires-Python: >=3.11
License-File: LICENSE
